eam_onb_helper/__init__.py
eam_onb_helper/emp.py
eam_onb_helper/vend.py
eam_onb_helper/vendor_list.py
eam_onb_helper/common/__init__.py
eam_onb_helper/common/helpers.py
eam_onb_helper-0.1.0.dist-info/METADATA
eam_onb_helper-0.1.0.dist-info/WHEEL
eam_onb_helper-0.1.0.dist-info/licenses/LICENSE
eam_onb_helper-0.1.0.dist-info/RECORD
